koap/__init__.py
koap/api-telematik/.git
koap/api-telematik/.gitignore
koap/api-telematik/CODE_OF_CONDUCT.md
koap/api-telematik/CONTRIBUTING.md
koap/api-telematik/LICENSE
koap/api-telematik/Readme.md
koap/api-telematik/ReleaseNotes.md
koap/api-telematik/cm/cc/CCS.wsdl
koap/api-telematik/cm/cc/CmCcCommon.xsd
koap/api-telematik/cm/cc/CmCcServiceRequest.xsd
koap/api-telematik/cm/cc/CmCcServiceResponse.xsd
koap/api-telematik/cm/common/CmCommon.xsd
koap/api-telematik/cm/uf/CmUfServiceRequest.xsd
koap/api-telematik/cm/uf/CmUfServiceResponse.xsd
koap/api-telematik/cm/uf/UFS.wsdl
koap/api-telematik/conn/AuthSignatureService.wsdl
koap/api-telematik/conn/AuthSignatureService_v7_4_1.wsdl
koap/api-telematik/conn/CardEvents.xsd
koap/api-telematik/conn/CardService.wsdl
koap/api-telematik/conn/CardService.xsd
koap/api-telematik/conn/CardServiceCommon.xsd
koap/api-telematik/conn/CardService_v8_1_1.wsdl
koap/api-telematik/conn/CardService_v8_1_1.xsd
koap/api-telematik/conn/CardService_v8_1_2.wsdl
koap/api-telematik/conn/CardService_v8_1_3.xsd
koap/api-telematik/conn/CardTerminalInfo.xsd
koap/api-telematik/conn/CardTerminalService.wsdl
koap/api-telematik/conn/CardTerminalService.xsd
koap/api-telematik/conn/CertificateService.wsdl
koap/api-telematik/conn/CertificateService.xsd
koap/api-telematik/conn/CertificateServiceCommon.xsd
koap/api-telematik/conn/CertificateService_v6_0_1.wsdl
koap/api-telematik/conn/CertificateService_v6_0_2.xsd
koap/api-telematik/conn/ConnectorCommon.xsd
koap/api-telematik/conn/ConnectorContext.xsd
koap/api-telematik/conn/EncryptionService.wsdl
koap/api-telematik/conn/EncryptionService.xsd
koap/api-telematik/conn/EncryptionService_v6_1_1.wsdl
koap/api-telematik/conn/EncryptionService_v6_1_2.xsd
koap/api-telematik/conn/EventService.wsdl
koap/api-telematik/conn/EventService.xsd
koap/api-telematik/conn/OperatingData.xsd
koap/api-telematik/conn/README.CardService.txt
koap/api-telematik/conn/ServiceDirectory.xsd
koap/api-telematik/conn/ServiceInformation.xsd
koap-0.4.0.dist-info/METADATA
koap-0.4.0.dist-info/WHEEL
koap-0.4.0.dist-info/RECORD
