Metadata-Version: 2.3
Name: koap
Version: 0.4.0
Summary: 
Author: Sergej Suskov
Author-email: git@spilikin.dev
Requires-Python: >=3.10,<3.13
Classifier: Programming Language :: Python :: 3
Classifier: Programming Language :: Python :: 3.10
Classifier: Programming Language :: Python :: 3.11
Classifier: Programming Language :: Python :: 3.12
Requires-Dist: jwcrypto (>=1.5.0,<2.0.0)
Requires-Dist: pydantic (>=1.10.2,<2.0.0)
Requires-Dist: pyopenssl (>=23.2.0,<24.0.0)
Requires-Dist: requests (>=2.28.1,<3.0.0)
Requires-Dist: requests-pkcs12 (>=1.18,<2.0)
Requires-Dist: rich (>=12.5.1,<13.0.0)
Requires-Dist: xmltodict (>=0.13.0,<0.14.0)
Requires-Dist: zeep (>=4.1.0,<5.0.0)
